odoo/addons/shopinvader_payment_paypal/README.rst
odoo/addons/shopinvader_payment_paypal/__init__.py
odoo/addons/shopinvader_payment_paypal/__manifest__.py
odoo/addons/shopinvader_payment_paypal/controllers/__init__.py
odoo/addons/shopinvader_payment_paypal/controllers/main.py
odoo/addons/shopinvader_payment_paypal/demo/shopinvader_payment.xml
odoo/addons/shopinvader_payment_paypal/i18n/shopinvader_payment_paypal.pot
odoo/addons/shopinvader_payment_paypal/readme/CONTRIBUTORS.rst
odoo/addons/shopinvader_payment_paypal/readme/DESCRIPTION.rst
odoo/addons/shopinvader_payment_paypal/services/__init__.py
odoo/addons/shopinvader_payment_paypal/services/payment_paypal.py
odoo/addons/shopinvader_payment_paypal/static/description/index.html
odoo/addons/shopinvader_payment_paypal/tests/__init__.py
odoo/addons/shopinvader_payment_paypal/tests/test_shopinvader_paypal.py
odoo13_addon_shopinvader_payment_paypal-13.0.2.0.1.dist-info/METADATA
odoo13_addon_shopinvader_payment_paypal-13.0.2.0.1.dist-info/WHEEL
odoo13_addon_shopinvader_payment_paypal-13.0.2.0.1.dist-info/top_level.txt
odoo13_addon_shopinvader_payment_paypal-13.0.2.0.1.dist-info/RECORD
