Metadata-Version: 2.1
Name: odoo13-addon-shopinvader-payment-paypal
Version: 13.0.2.0.1
Summary: Shopinvader REST Services for Paypal Payments
Home-page: https://github.com/shopinvader/odoo-shopinvader-payment
Author: Akretion
License: AGPL-3
Platform: UNKNOWN
Classifier: Programming Language :: Python
Classifier: Framework :: Odoo
Classifier: License :: OSI Approved :: GNU Affero General Public License v3
Requires-Python: >=3.5
Requires-Dist: odoo13-addon-invader-payment-paypal
Requires-Dist: odoo13-addon-shopinvader-payment
Requires-Dist: odoo (<13.1dev,>=13.0a)
